corebridge/__init__.py
corebridge/_modidx.py
corebridge/aicorebridge.py
corebridge/compose.py
corebridge/core.py
corebridge/rscript.py
corebridge/timeseriesdataframe.py
corebridge-0.6.6.dist-info/licenses/LICENSE
corebridge-0.6.6.dist-info/WHEEL
corebridge-0.6.6.dist-info/METADATA
corebridge-0.6.6.dist-info/RECORD
