Metadata-Version: 2.4
Name: corebridge
Version: 0.6.6
Summary: Corebridge - a bridge between Univia AICore platform and Wodan processor modules
Author-email: Fenke Meijer <fenkemeijer@gmail.com>
Requires-Python: >=3.10
License-Expression: Apache-2.0
Classifier: Development Status :: 3 - Alpha
Classifier: Framework :: Jupyter
Classifier: Intended Audience :: Developers
Classifier: Intended Audience :: Science/Research
Classifier: Programming Language :: Python :: 3 :: Only
Classifier: Topic :: Scientific/Engineering
Classifier: Topic :: Utilities
License-File: LICENSE
Requires-Dist: python-dateutil
Requires-Dist: pytz
Requires-Dist: numpy
Requires-Dist: pandas
Requires-Dist: scipy
Requires-Dist: scikit-learn
Requires-Dist: fastcore
Requires-Dist: python-dateutil ; extra == "dev"
Requires-Dist: pytz ; extra == "dev"
Requires-Dist: numpy ; extra == "dev"
Requires-Dist: pandas ; extra == "dev"
Requires-Dist: scipy ; extra == "dev"
Requires-Dist: scikit-learn ; extra == "dev"
Requires-Dist: fastcore ; extra == "dev"
Requires-Dist: jupyter ; extra == "dev"
Requires-Dist: jupyter_contrib_nbextensions ; extra == "dev"
Requires-Dist: jupyterlab-git ; extra == "dev"
Requires-Dist: jupyterlab-quarto ; extra == "dev"
Requires-Dist: nbdev ; extra == "dev"
Requires-Dist: aiohttp ; extra == "dev"
Requires-Dist: asyncpg ; extra == "dev"
Requires-Dist: tabulate ; extra == "dev"
Requires-Dist: rdata ; extra == "dev"
Project-URL: Documentation, https://fenke.github.io/corebridge/
Project-URL: Home, https://github.com/fenke/corebridge
Provides-Extra: dev
